moonraker_api/__init__.py
moonraker_api/const.py
moonraker_api/moonrakerclient.py
moonraker_api/websockets/__init__.py
moonraker_api/websockets/awaitabletask.py
moonraker_api/websockets/websocketclient.py
moonraker_api/websockets/websocketdatahandler.py
moonraker_api-2.0.6.dist-info/LICENSE.txt
moonraker_api-2.0.6.dist-info/METADATA
moonraker_api-2.0.6.dist-info/WHEEL
moonraker_api-2.0.6.dist-info/top_level.txt
moonraker_api-2.0.6.dist-info/RECORD
