Metadata-Version: 2.1
Name: moonraker-api
Version: 2.0.6
Summary: Async websocket API client for Moonraker
Home-page: https://github.com/cmroche/moonraker-api
Author: Clifford Roche
Author-email: 
Classifier: Programming Language :: Python :: 3
Classifier: License :: OSI Approved :: GNU General Public License v3 (GPLv3)
Classifier: Operating System :: OS Independent
Requires-Python: >=3.8
License-File: LICENSE.txt
Requires-Dist: aiohttp ~=3.8
Requires-Dist: async-timeout ~=4.0
